primal/__init__.py
primal/version.py
primal/tests/__init__.py
primal/tests/tests.py
primal-0.1.dist-info/DESCRIPTION.rst
primal-0.1.dist-info/METADATA
primal-0.1.dist-info/RECORD
primal-0.1.dist-info/WHEEL
primal-0.1.dist-info/metadata.json
primal-0.1.dist-info/top_level.txt
